README.rst
setup.cfg
setup.py
should_be/__init__.py
should_be/all.py
should_be/core.py
should_be/extensions/__init__.py
should_be/extensions/container.py
should_be/extensions/iterable.py
should_be/extensions/mapping.py
should_be/extensions/numeric.py
should_be/extensions/py3_compat.py
should_be/extensions/sequence.py
should_be/extensions/set.py
should_be/extensions/sized.py
should_be/extensions/string.py
should_be/tests/__init__.py
should_be/tests/test_container_mixin.py
should_be/tests/test_iterable_mixin.py
should_be/tests/test_mixin_utils.py
should_be/tests/test_number_mixins.py
should_be/tests/test_object_mixin.py
should_be/tests/test_py3compat_mixin.py
should_be/tests/test_sequence_mixin.py
should_be/tests/test_set_mixin.py
should_be/tests/test_sized_mixin.py
should_be/tests/test_string_mixin.py
shouldbe.egg-info/PKG-INFO
shouldbe.egg-info/SOURCES.txt
shouldbe.egg-info/dependency_links.txt
shouldbe.egg-info/requires.txt
shouldbe.egg-info/top_level.txt