Metadata-Version: 1.1
Name: shouldbe
Version: 0.1.1
Summary: Python Assertion Helpers inspired by Shouldly
Home-page: https://github.com/directxman12/should_be
Author: Solly Ross
Author-email: sross@redhat.com
License: LICENSE.txt
Keywords: testing,assertions
Platform: UNKNOWN
Classifier: Development Status :: 4 - Beta
Classifier: Programming Language :: Python
Classifier: Programming Language :: Python :: 2.7
Classifier: Programming Language :: Python :: 3
Classifier: Programming Language :: Python :: 3.3
Classifier: Intended Audience :: Developers
Classifier: License :: OSI Approved :: ISC License (ISCL)
Classifier: Programming Language :: Python :: Implementation :: CPython
Classifier: Topic :: Software Development :: Libraries :: Python Modules
